[
  {
    "id": "2026-06-06-gelonghuicom-ceoai50ai",
    "date": "2026-06-06",
    "title": "软银CEO孙正义：AI规模将是互联网泡沫的50倍，下一个万亿赛道是物理AI、机器人",
    "category": [
      "robotics"
    ],
    "region": "Global",
    "summary": "软银CEO孙正义：AI规模将是互联网泡沫的50倍，下一个万亿赛道是物理AI、机器人",
    "source": "gelonghui.com",
    "source_url": "https://www.gelonghui.com/p/5089402",
    "tags": [],
    "impact": ""
  },
  {
    "id": "2026-06-06-36krcom-",
    "date": "2026-06-06",
    "title": "比亚迪玩跨界？进军人形机器人，代号“尧舜禹”",
    "category": [
      "humanoid",
      "robotics"
    ],
    "region": "Global",
    "summary": "比亚迪玩跨界？进军人形机器人，代号“尧舜禹”",
    "source": "36kr.com",
    "source_url": "https://www.36kr.com/p/3840170310502663",
    "tags": [],
    "impact": ""
  },
  {
    "id": "2026-06-06-the-robot-report-",
    "date": "2026-06-06",
    "title": "机器人可以增强制造业工人而不是取代他们",
    "category": [
      "robotics"
    ],
    "region": "Global",
    "summary": "With the right AI, teleoperation, and safeguards, robotics can augment manufacturing opportunities, says one to ONE Holdings' president. The post Robots can enhance manufacturing workers rather than replace them appeared first on The Robot Report .（原题：Robots can enhance manufacturing workers rather than replace them）",
    "source": "The Robot Report",
    "source_url": "https://www.therobotreport.com/robots-can-enhance-manufacturing-workers-rather-than-replace-them/",
    "tags": [],
    "impact": "Sat, 06 Jun 2026 12:30:12 +0000"
  },
  {
    "id": "2026-06-06-36krcom-",
    "date": "2026-06-06",
    "title": "拆解机器人“肉身”、量产与供应链：空翻之后，它还要学会接住一片落叶",
    "category": [
      "robotics"
    ],
    "region": "Global",
    "summary": "拆解机器人“肉身”、量产与供应链：空翻之后，它还要学会接住一片落叶",
    "source": "36kr.com",
    "source_url": "https://www.36kr.com/p/3835876543806340",
    "tags": [],
    "impact": ""
  },
  {
    "id": "2026-06-06-36krcom-",
    "date": "2026-06-06",
    "title": "宇树、智元的线下门店叙事：具身智能正入迈进商业周期",
    "category": [
      "humanoid"
    ],
    "region": "Global",
    "summary": "宇树、智元的线下门店叙事：具身智能正入迈进商业周期",
    "source": "36kr.com",
    "source_url": "https://www.36kr.com/p/3840074519611651",
    "tags": [],
    "impact": ""
  },
  {
    "id": "2026-06-06-xueqiucom-",
    "date": "2026-06-06",
    "title": "关于具身智能机器人投资的思考",
    "category": [
      "humanoid",
      "robotics"
    ],
    "region": "Global",
    "summary": "关于具身智能机器人投资的思考",
    "source": "xueqiu.com",
    "source_url": "http://xueqiu.com/1665500619/392684166",
    "tags": [],
    "impact": ""
  },
  {
    "id": "2026-06-06-ifanrcom--ai-",
    "date": "2026-06-06",
    "title": "从感知智能到智能体 AI：高通汽车中国布局深化加速 公司",
    "category": [
      "general"
    ],
    "region": "Global",
    "summary": "从感知智能到智能体 AI：高通汽车中国布局深化加速 公司",
    "source": "ifanr.com",
    "source_url": "https://www.ifanr.com/1668242",
    "tags": [],
    "impact": ""
  },
  {
    "id": "2026-06-06-36krcom-agent-",
    "date": "2026-06-06",
    "title": "互联网变天：机器人流量首次反超人类，Agent 时代拉开大幕",
    "category": [
      "robotics"
    ],
    "region": "Global",
    "summary": "互联网变天：机器人流量首次反超人类，Agent 时代拉开大幕",
    "source": "36kr.com",
    "source_url": "https://www.36kr.com/p/3839937467419143",
    "tags": [],
    "impact": ""
  },
  {
    "id": "2026-06-06-geekparknet-genesis-ai-",
    "date": "2026-06-06",
    "title": "Genesis AI 发布新模型：机器人开始挑战西红柿炒鸡蛋",
    "category": [
      "robotics"
    ],
    "region": "Global",
    "summary": "Genesis AI 发布新模型：机器人开始挑战西红柿炒鸡蛋",
    "source": "geekpark.net",
    "source_url": "http://www.geekpark.net/news/363905",
    "tags": [],
    "impact": ""
  },
  {
    "id": "2026-06-06-geekparknet-figure-ai--demo",
    "date": "2026-06-06",
    "title": "Figure AI 发布新 demo：两个机器人点头致意，我们一起把被子拉开",
    "category": [
      "robotics"
    ],
    "region": "Global",
    "summary": "Figure AI 发布新 demo：两个机器人点头致意，我们一起把被子拉开",
    "source": "geekpark.net",
    "source_url": "http://www.geekpark.net/news/363963",
    "tags": [],
    "impact": ""
  },
  {
    "id": "2026-06-05-cnbc-technology-",
    "date": "2026-06-05",
    "title": "科技巨头继续人工智能裁员，亚马逊推出最新仓库机器人",
    "category": [
      "robotics"
    ],
    "region": "Global",
    "summary": "\"Our experience of robots is that it's actually driven up employment rather than the reverse,\" Amazon executive John Boumphrey told CNBC.（原题：Amazon unveils latest warehouse robot as tech giants continue AI layoffs）",
    "source": "CNBC Technology",
    "source_url": "https://www.cnbc.com/2026/06/05/amazon-robot-proteus-warehouse-ai-layoffs.html",
    "tags": [],
    "impact": "Fri, 05 Jun 2026 22:53:20 GMT"
  },
  {
    "id": "2026-06-05-guokrcom-",
    "date": "2026-06-05",
    "title": "我长大以后的梦想，是去测评仿生机器人",
    "category": [
      "robotics"
    ],
    "region": "Global",
    "summary": "我长大以后的梦想，是去测评仿生机器人",
    "source": "guokr.com",
    "source_url": "https://www.guokr.com/article/469359/",
    "tags": [],
    "impact": ""
  },
  {
    "id": "2026-06-05-ieee-spectrum-robotics-",
    "date": "2026-06-05",
    "title": "周五视频：观看这个跑步机器人不会从楼梯上摔下来",
    "category": [
      "robotics"
    ],
    "region": "Global",
    "summary": "Video Friday is your weekly selection of awesome robotics videos, collected by your friends at IEEE Spectrum robotics. We also post a weekly calendar of upcoming robotics events for the next few months. Please send us your events for inclusion. RSS 2026 : 13–17 July 2026, SYDNEY Summer School on Multi-Robot Systems : 29 July–4 August 2026, PRAGUE Actuate 2026 : 18–19 August 2026, SAN FRANCISCO Enjoy today’s videos! It’s been a while since a humanoid robot video actually impressed me, but the beginning of this does. Hard to know how much of that recovery was luck, though. [ Deep Robotics ] When you’re very confident in your MPC-based balance controller... I feel you, buddy. And thanks for posting this. We’ve all been there, in one way or another. [ DARoS Lab ] GENE01 designed from scratch and sent to batch production. Two scalable lower bodies. Physical AI deployed for motor control and world-action modeling. All in three months. Generative Bionics is running. [ Generative Bionics ] Alex, the newest humanoid robot built entirely by ‪IHMCRobotics‬, takes its first steps outdoors! This was a significant milestone for our team, especially because Alex is the first humanoid robot developed entirely by IHMC Robotics to venture outside the lab. These outdoor trials were conducted in preparation for a demonstration in Maryland, where Alex later successfully walked completely untethered. [ IHMC ] Built on the Enlight platform, Flexiv Mico is a compact dual-arm system engineered for safe, seamless collaboration in any workspace. [ Flexiv Robotics ] Is it weird that I’m jealous that robots can have feet that are swappable? [ Boston Dynamics ] Midweek at ICRA 2026. Cable-climbing robots that work as a squad: CCRobot-S is a team of robots with reconfigurable cable-driven manipulation that collaboratively inspect and maintain long-span bridge stay cables. Parallel operation for speed, morphological reconfiguration for reach. [ IEEE Transactions on Robotics ] I would love to know the story behind this odd choice of hat. [ Robotis ] How did Atlas learn football—and why? Go behind the scenes of School of Football and discover a glimpse of the Next of robotics. What I really want to know is, what kinds of things is it possible to do in football ( soccer ) when your robot’s joints are not constrained by biology? [ Boston Dynamics ]（原题：Video Friday: Watch This Running Robot Not Fall Down Stairs）",
    "source": "IEEE Spectrum Robotics",
    "source_url": "https://spectrum.ieee.org/video-friday-humanoid-robot-running",
    "tags": [],
    "impact": "Fri, 05 Jun 2026 15:30:01 +0000"
  },
  {
    "id": "2026-06-05-the-robot-report-",
    "date": "2026-06-05",
    "title": "为什么确定性实时系统在机器人技术中比以往任何时候都更加重要",
    "category": [
      "robotics"
    ],
    "region": "Global",
    "summary": "Winston Leung discusses the role of QNX role in robotics and AI, focusing on safety, innovation, and industry trends. The post Why deterministic real-time systems are more critical than ever in robotics appeared first on The Robot Report .（原题：Why deterministic real-time systems are more critical than ever in robotics）",
    "source": "The Robot Report",
    "source_url": "https://www.therobotreport.com/qnx-why-deterministic-real-time-systems-are-more-critical-than-ever-robotics/",
    "tags": [],
    "impact": "Fri, 05 Jun 2026 18:49:11 +0000"
  },
  {
    "id": "2026-06-05-ai-botcn-pawbench--",
    "date": "2026-06-05",
    "title": "PawBench – 阿里通义推出的通用智能体评测基准",
    "category": [
      "general"
    ],
    "region": "Global",
    "summary": "PawBench – 阿里通义推出的通用智能体评测基准",
    "source": "ai-bot.cn",
    "source_url": "https://ai-bot.cn/pawbench/",
    "tags": [],
    "impact": ""
  },
  {
    "id": "2026-06-05-the-robot-report-genisom-ai--icra-2026-",
    "date": "2026-06-05",
    "title": "GENISOM AI 在 ICRA 2026 上首次推出可部署机器人平台",
    "category": [
      "robotics"
    ],
    "region": "Global",
    "summary": "At ICRA 2026, GENISOM AI may have been new to many international attendees — but it is not a concept-stage robotics startup. The post GENISOM AI debuts deployable robotics platforms at ICRA 2026 appeared first on The Robot Report .（原题：GENISOM AI debuts deployable robotics platforms at ICRA 2026）",
    "source": "The Robot Report",
    "source_url": "https://www.therobotreport.com/genisom-ai-debuts-deployable-robotics-platforms-icra-2026/",
    "tags": [],
    "impact": "Fri, 05 Jun 2026 15:30:40 +0000"
  }
]