[
  {
    "id": "2026-04-26-36krcom-68",
    "date": "2026-04-26",
    "title": "68亿，具身机器人史上最大采购来了",
    "category": [
      "humanoid",
      "robotics"
    ],
    "region": "Global",
    "summary": "68亿，具身机器人史上最大采购来了",
    "source": "36kr.com",
    "source_url": "https://www.36kr.com/p/3780742359243776",
    "tags": [],
    "impact": ""
  },
  {
    "id": "2026-04-24-ifanrcom--7-",
    "date": "2026-04-24",
    "title": "腾讯发布了 7 个座舱智能体，汽车的意义从「空间位移」走向了「时间价值」董车会",
    "category": [
      "general"
    ],
    "region": "Global",
    "summary": "腾讯发布了 7 个座舱智能体，汽车的意义从「空间位移」走向了「时间价值」董车会",
    "source": "ifanr.com",
    "source_url": "https://www.ifanr.com/1663788",
    "tags": [],
    "impact": ""
  },
  {
    "id": "2026-04-24-the-robot-report-ss-innovations-",
    "date": "2026-04-24",
    "title": "SS Innovations 正在开发基于无人机的手术机器人",
    "category": [
      "defense",
      "robotics"
    ],
    "region": "Global",
    "summary": "SS Innovations designed the SSi Vimana Aero to bring robotic surgical care directly to wounded soldiers. It is also working on a surgical humanoid. The post SS Innovations is developing a drone-based surgical robot appeared first on The Robot Report .（原题：SS Innovations is developing a drone-based surgical robot）",
    "source": "The Robot Report",
    "source_url": "https://www.therobotreport.com/ss-innovations-is-developing-a-drone-based-surgical-robot/",
    "tags": [],
    "impact": "Fri, 24 Apr 2026 12:30:59 +0000"
  },
  {
    "id": "2026-04-24-ai-botcn-jvs-crew--",
    "date": "2026-04-24",
    "title": "JVS Crew – 阿里云推出的企业级智能体构建平台",
    "category": [
      "general"
    ],
    "region": "Global",
    "summary": "JVS Crew – 阿里云推出的企业级智能体构建平台",
    "source": "ai-bot.cn",
    "source_url": "https://ai-bot.cn/jvs-crew/",
    "tags": [],
    "impact": ""
  }
]